fastapi_users_db_dynamodb/__init__.py
fastapi_users_db_dynamodb/_generics.py
fastapi_users_db_dynamodb/access_token.py
fastapi_users_db_dynamodb/attributes.py
fastapi_users_db_dynamodb/config.py
fastapi_users_db_dynamodb/py.typed
fastapi_users_db_dynamodb/tables.py
fastapi_users_db_dynamodb-1.0.4.dist-info/METADATA
fastapi_users_db_dynamodb-1.0.4.dist-info/WHEEL
fastapi_users_db_dynamodb-1.0.4.dist-info/licenses/LICENSE
fastapi_users_db_dynamodb-1.0.4.dist-info/RECORD
