Metadata-Version: 2.4
Name: fastapi-users-db-dynamodb
Version: 1.0.4
Summary: FastAPI Users database adapter for AWS DynamoDB
Project-URL: Documentation, https://fastapi-users.github.io/fastapi-users
Project-URL: Source, https://github.com/AppSolves/fastapi-users-db-dynamodb
Author-email: Kaan Gönüldinc <contact@appsolves.dev>
License-Expression: Apache-2.0
License-File: LICENSE
Classifier: Development Status :: 5 - Production/Stable
Classifier: Framework :: AsyncIO
Classifier: Framework :: FastAPI
Classifier: Intended Audience :: Developers
Classifier: Programming Language :: Python :: 3 :: Only
Classifier: Programming Language :: Python :: 3.11
Classifier: Programming Language :: Python :: 3.12
Classifier: Programming Language :: Python :: 3.13
Classifier: Topic :: Internet :: WWW/HTTP :: Session
Requires-Python: >=3.11
Requires-Dist: as-aiopynamodb>=1.0.1
Requires-Dist: fastapi-users>=14.0.0
